nameplate/__init__.py
nameplate/_version.py
nameplate/remote_server.py
nameplate/schemas.py
nameplate/server.py
nameplate/data/__init__.py
nameplate/data/nameplate.db
nameplate/tools/__init__.py
nameplate/tools/parse.py
py_nameplate-1.0.dist-info/METADATA
py_nameplate-1.0.dist-info/WHEEL
py_nameplate-1.0.dist-info/entry_points.txt
py_nameplate-1.0.dist-info/licenses/LICENSE
py_nameplate-1.0.dist-info/RECORD
