Metadata-Version: 2.4
Name: py-nameplate
Version: 1.0
Summary: MCP server and library for parsing US addresses and names into structured components
Author: Danny Heskett
License: BSD-3-Clause
License-File: LICENSE
Keywords: address,mcp,name,parser,parsing
Classifier: Development Status :: 4 - Beta
Classifier: Intended Audience :: Developers
Classifier: License :: OSI Approved :: BSD License
Classifier: Programming Language :: Python :: 3
Classifier: Programming Language :: Python :: 3.12
Classifier: Topic :: Text Processing
Requires-Python: >=3.12
Requires-Dist: mcp>=1.8.0
Requires-Dist: pydantic>=2.0
Provides-Extra: dev
Requires-Dist: pytest-asyncio>=0.21; extra == 'dev'
Requires-Dist: pytest-cov>=4.0; extra == 'dev'
Requires-Dist: pytest>=7.0; extra == 'dev'
Requires-Dist: ruff>=0.1.0; extra == 'dev'
Provides-Extra: remote
Requires-Dist: sse-starlette>=2.0.0; extra == 'remote'
Requires-Dist: starlette>=0.35.0; extra == 'remote'
Requires-Dist: uvicorn>=0.23.0; extra == 'remote'
